karix/__init__.py
karix/api_client.py
karix/configuration.py
karix/rest.py
karix/api/__init__.py
karix/api/accounts_api.py
karix/api/message_api.py
karix/api/number_api.py
karix/api/number_search_api.py
karix/api/webhook_api.py
karix/models/__init__.py
karix/models/account.py
karix/models/account_number.py
karix/models/array_meta_response.py
karix/models/create_account.py
karix/models/create_message.py
karix/models/create_message_content.py
karix/models/create_message_content_location.py
karix/models/create_webhook.py
karix/models/edit_account.py
karix/models/edit_account_number.py
karix/models/edit_webhook.py
karix/models/inline_response200.py
karix/models/inline_response2001.py
karix/models/inline_response2002.py
karix/models/inline_response2003.py
karix/models/inline_response2004.py
karix/models/inline_response2005.py
karix/models/inline_response2006.py
karix/models/inline_response201.py
karix/models/inline_response2011.py
karix/models/inline_response2012.py
karix/models/inline_response202.py
karix/models/inline_response402.py
karix/models/inline_response402_error.py
karix/models/inline_response403.py
karix/models/inline_response403_error.py
karix/models/inline_response404.py
karix/models/inline_response404_error.py
karix/models/inline_response500.py
karix/models/inline_response500_error.py
karix/models/message.py
karix/models/message_channel_details.py
karix/models/message_channel_details_sms.py
karix/models/message_channel_details_whatsapp.py
karix/models/message_content.py
karix/models/message_content_location.py
karix/models/message_error.py
karix/models/meta_response.py
karix/models/meta_response_with_balance.py
karix/models/object_meta_response.py
karix/models/phone_number.py
karix/models/phone_number_rate.py
karix/models/phone_number_region.py
karix/models/phone_number_service.py
karix/models/rent_number.py
karix/models/webhook.py
test/__init__.py
test/test_account.py
test/test_account_number.py
test/test_accounts_api.py
test/test_array_meta_response.py
karix-2.0.0.dist-info/LICENSE
karix-2.0.0.dist-info/METADATA
karix-2.0.0.dist-info/WHEEL
karix-2.0.0.dist-info/top_level.txt
karix-2.0.0.dist-info/RECORD
